setup.py
constants_manager/__init__.py
constants_manager/constants_manager.py
constants_manager.egg-info/PKG-INFO
constants_manager.egg-info/SOURCES.txt
constants_manager.egg-info/dependency_links.txt
constants_manager.egg-info/top_level.txt
constants_manager.egg-info/zip-safe