Metadata-Version: 1.1
Name: constants-manager
Version: 1.0.1
Summary: a library of managing constants.
Home-page: https://github.com/masudaK/constants_manager
Author: Kenichi Masuda
Author-email: masuken@gmail.com
License: MIT
Platform: Linux
Classifier: Topic :: Software Development :: Libraries :: Python Modules
Classifier: License :: OSI Approved :: MIT License
Classifier: Programming Language :: Python :: 3
